CHANGELOG.rst
LICENSE.txt
MANIFEST.in
README.rst
requirements.txt
setup.py
bin/abclinuxu_uploader.py
docs/Makefile
docs/__init__.py
docs/__init__.pyc
docs/conf.py
docs/index.rst
docs/requirements.txt
docs/api/abclinuxuapi.rst
docs/api/blogpost.rst
docs/api/comment.rst
docs/api/concept.rst
docs/api/shared.rst
docs/api/user.rst
src/abclinuxuapi/__init__.py
src/abclinuxuapi/blogpost.py
src/abclinuxuapi/comment.py
src/abclinuxuapi/concept.py
src/abclinuxuapi/shared.py
src/abclinuxuapi/user.py
src/abclinuxuapi.egg-info/PKG-INFO
src/abclinuxuapi.egg-info/SOURCES.txt
src/abclinuxuapi.egg-info/dependency_links.txt
src/abclinuxuapi.egg-info/not-zip-safe
src/abclinuxuapi.egg-info/requires.txt
src/abclinuxuapi.egg-info/top_level.txt
tests/test_blogpost.py
tests/test_comment.py
tests/test_init.py
tests/test_shared.py
tests/test_user.py