Metadata-Version: 1.1
Name: abclinuxuapi
Version: 0.4.14
Summary: API for http://abclinuxu.cz.
Home-page: https://github.com/Bystroushaak/abclinuxuapi
Author: Bystroushaak
Author-email: bystrousak@kitakitsune.org
License: MIT
Platform: UNKNOWN
Classifier: Development Status :: 3 - Alpha
Classifier: Intended Audience :: Developers
Classifier: Programming Language :: Python :: 2
Classifier: Programming Language :: Python :: 2.7
Classifier: Topic :: Internet
Classifier: Topic :: Internet :: WWW/HTTP :: Site Management
Classifier: Topic :: Software Development :: Libraries
Classifier: Topic :: Software Development :: Libraries :: Python Modules
Classifier: Topic :: Utilities
Classifier: Natural Language :: Czech
Classifier: License :: OSI Approved :: MIT License
